picodaqa/BarDisplay.py
picodaqa/BufferMan.py
picodaqa/DataGraphs.py
picodaqa/DataLogger.py
picodaqa/Oscilloscope.py
picodaqa/RMeter.py
picodaqa/VoltMeter.py
picodaqa/__init__.py
picodaqa/_version_info.py
picodaqa/animHists.py
picodaqa/mpBDisplay.py
picodaqa/mpBufManCntrl.py
picodaqa/mpDataGraphs.py
picodaqa/mpDataLogger.py
picodaqa/mpHists.py
picodaqa/mpOsci.py
picodaqa/mpRMeter.py
picodaqa/mpVMeter.py
picodaqa/picoConfig.py
picodaqa/picolog1000Config.py
picodaqa/plotBufManInfo.py
picodaqa/read_config.py
picodaqa-1.1.5.dist-info/AUTHORS
picodaqa-1.1.5.dist-info/LICENSE
picodaqa-1.1.5.dist-info/METADATA
picodaqa-1.1.5.dist-info/WHEEL
picodaqa-1.1.5.dist-info/top_level.txt
picodaqa-1.1.5.dist-info/RECORD
