Metadata-Version: 2.1
Name: picodaqa
Version: 1.1.5
Summary: Data AcQuisition and analysis with PicoScope usb-oscilloscopes
Home-page: https://www.etp.kit.edu/~quast/
Author: Guenter Quast
Author-email: Guenter.Quast@online.de
License: GNU Public Licence
Classifier: Development Status :: 5 - Production/Stable
Classifier: Programming Language :: Python :: 3.6
Classifier: Programming Language :: Python :: 3.7
Classifier: Programming Language :: Python :: 3.8
Classifier: Programming Language :: Python :: 3.9
Classifier: Programming Language :: Python :: 3.10
Classifier: Programming Language :: Python :: 3.11
Classifier: Programming Language :: Python :: 3.12
License-File: LICENSE
License-File: AUTHORS
